uvn/__init__.py
uvn/__main__.py
uvn/cli.py
uvn/core.py
uvn-0.1.0.dist-info/METADATA
uvn-0.1.0.dist-info/WHEEL
uvn-0.1.0.dist-info/entry_points.txt
uvn-0.1.0.dist-info/licenses/LICENSE
uvn-0.1.0.dist-info/RECORD
