Metadata-Version: 2.1
Name: uvn
Version: 0.1.0
Summary: uvn is conda for uv; a centralized Python virtual environment manager.
Project-URL: Homepage, https://github.com/xmodar/uvn
Author-email: "Modar M. Alfadly" <modar.alfadly@gmail.com>
License: MIT License
License-File: LICENSE
Keywords: conda,uv,uvenv,uvn,venv,virtualenv
Classifier: Development Status :: 3 - Alpha
Classifier: Intended Audience :: Developers
Classifier: License :: OSI Approved :: MIT License
Classifier: Programming Language :: Python :: 3
Classifier: Programming Language :: Python :: 3.7
Classifier: Programming Language :: Python :: 3.8
Classifier: Programming Language :: Python :: 3.9
Classifier: Programming Language :: Python :: 3.10
Classifier: Programming Language :: Python :: 3.11
Classifier: Programming Language :: Python :: 3.12
Classifier: Programming Language :: Python :: 3.13
Classifier: Topic :: Software Development
Requires-Python: >=3.7
Provides-Extra: cli
Requires-Dist: rich; extra == 'cli'
Requires-Dist: shellingham; extra == 'cli'
Requires-Dist: typer; extra == 'cli'
Requires-Dist: typing-extensions; extra == 'cli'
